{
  "asset": {
    "version": "0.0"
  },
  "geometricError": 4,
  "root": {
    "children": [
      {
        "content": {
          "url": "Tiles/0_0/0_0.pnts"
        },
        "boundingVolume": {
          "region": [
            -2.1478828827309155,
            0.7689004565861249,
            -2.1478794807713144,
            0.768904018428758,
            7.4676,
            14.612112
          ]
        },
        "geometricError": 2,
        "refine": "replace"
      },
      {
        "content": {
          "url": "Tiles/0_1/0_1.pnts"
        },
        "boundingVolume": {
          "region": [
            -2.1478793299270493,
            0.768900536642849,
            -2.1478759279549395,
            0.7689040984793978,
            7.357871999999996,
            8.052816000000005
          ]
        },
        "geometricError": 2,
        "refine": "replace"
      },
      {
        "content": {
          "url": "Tiles/1_0/1_0.pnts"
        },
        "boundingVolume": {
          "region": [
            -2.147883033587139,
            0.7689039383717661,
            -2.1478796316165956,
            0.7689075002145759,
            6.406895999999994,
            10.591800000000001
          ]
        },
        "geometricError": 2,
        "refine": "replace"
      },
      {
        "content": {
          "url": "Tiles/1_1/1_1.pnts"
        },
        "boundingVolume": {
          "region": [
            -2.1478794807713144,
            0.768904018428758,
            -2.1478760787882623,
            0.7689075802654837,
            6.397752000000003,
            14.636495999999996
          ]
        },
        "geometricError": 2,
        "refine": "replace"
      }
    ],
    "content": {
      "url": "root.pnts"
    },
    "boundingVolume": {
      "region": [
        -2.1478828827309155,
        0.7689004565861249,
        -2.1478760787882623,
        0.7689075802654837,
        6.397752000000003,
        14.636495999999996
      ]
    },
    "geometricError": 4,
    "refine": "replace"
  }
}