{
  "asset": {
    "version": "0.0"
  },
  "geometricError": 4,
  "root": {
    "children": [
      {
        "content": {
          "url": "Tiles/0_0/0_0.pnts"
        },
        "boundingVolume": {
          "region": [
            -2.1479007159188948,
            0.7689836991000283,
            -2.1478973137467134,
            0.7689872609712239,
            5.657088000000001,
            15.636240000000004
          ]
        },
        "geometricError": 2,
        "refine": "replace"
      },
      {
        "content": {
          "url": "Tiles/0_1/0_1.pnts"
        },
        "boundingVolume": {
          "region": [
            -2.1478971628302106,
            0.7689837791885944,
            -2.1478937606455184,
            0.768987341053705,
            5.596128000000005,
            27.477719999999994
          ]
        },
        "geometricError": 2,
        "refine": "replace"
      },
      {
        "content": {
          "url": "Tiles/1_0/1_0.pnts"
        },
        "boundingVolume": {
          "region": [
            -2.1479008668473583,
            0.76898718088239,
            -2.1478974646642337,
            0.7689907427537612,
            6.275831999999992,
            14.343888000000002
          ]
        },
        "geometricError": 2,
        "refine": "replace"
      },
      {
        "content": {
          "url": "Tiles/1_1/1_1.pnts"
        },
        "boundingVolume": {
          "region": [
            -2.1478973137467134,
            0.7689872609712239,
            -2.147893911551078,
            0.7689908228365098,
            5.882640000000004,
            16.337280000000007
          ]
        },
        "geometricError": 2,
        "refine": "replace"
      }
    ],
    "content": {
      "url": "root.pnts"
    },
    "boundingVolume": {
      "region": [
        -2.1479007159188948,
        0.7689836991000283,
        -2.147893911551078,
        0.7689908228365098,
        5.596128000000005,
        27.477719999999994
      ]
    },
    "geometricError": 4,
    "refine": "replace"
  }
}