{
  "asset": {
    "version": "0.0"
  },
  "geometricError": 4,
  "root": {
    "children": [
      {
        "content": {
          "url": "Tiles/0_0/0_0.pnts"
        },
        "boundingVolume": {
          "region": [
            -2.1478964903348188,
            0.7688862091565096,
            -2.1478930884690186,
            0.7688897710227753,
            7.805928000000004,
            14.627352000000004
          ]
        },
        "geometricError": 2,
        "refine": "replace"
      },
      {
        "content": {
          "url": "Tiles/0_1/0_1.pnts"
        },
        "boundingVolume": {
          "region": [
            -2.1478929375809868,
            0.7688862892375719,
            -2.147889535702677,
            0.7688898510977531,
            7.507223999999999,
            15.416783999999996
          ]
        },
        "geometricError": 2,
        "refine": "replace"
      },
      {
        "content": {
          "url": "Tiles/1_0/1_0.pnts"
        },
        "boundingVolume": {
          "region": [
            -2.1478966412348077,
            0.7688896909414447,
            -2.1478932393580656,
            0.7688932528078873,
            7.485888000000001,
            18.568416000000006
          ]
        },
        "geometricError": 2,
        "refine": "replace"
      },
      {
        "content": {
          "url": "Tiles/1_1/1_1.pnts"
        },
        "boundingVolume": {
          "region": [
            -2.1478930884690186,
            0.7688897710227753,
            -2.1478896865797674,
            0.7688933328831329,
            7.217664000000003,
            19.41576
          ]
        },
        "geometricError": 2,
        "refine": "replace"
      }
    ],
    "content": {
      "url": "root.pnts"
    },
    "boundingVolume": {
      "region": [
        -2.1478964903348188,
        0.7688862091565096,
        -2.1478896865797674,
        0.7688933328831329,
        7.217664000000003,
        19.41576
      ]
    },
    "geometricError": 4,
    "refine": "replace"
  }
}