{
  "asset": {
    "version": "0.0"
  },
  "geometricError": 4,
  "root": {
    "children": [
      {
        "content": {
          "url": "Tiles/0_0/0_0.pnts"
        },
        "boundingVolume": {
          "region": [
            -2.147940029614008,
            0.7689061383772055,
            -2.1479366278326704,
            0.7689097003175439,
            5.9436,
            10.244328000000005
          ]
        },
        "geometricError": 2,
        "refine": "replace"
      },
      {
        "content": {
          "url": "Tiles/0_1/0_1.pnts"
        },
        "boundingVolume": {
          "region": [
            -2.1479364767950386,
            0.7689062185361065,
            -2.147933075001191,
            0.7689097804703606,
            5.751576000000002,
            27.846528000000006
          ]
        },
        "geometricError": 2,
        "refine": "replace"
      },
      {
        "content": {
          "url": "Tiles/1_0/1_0.pnts"
        },
        "boundingVolume": {
          "region": [
            -2.147940180663598,
            0.7689096201583744,
            -2.14793677887132,
            0.7689131820988893,
            5.727192000000007,
            6.233159999999997
          ]
        },
        "geometricError": 2,
        "refine": "replace"
      },
      {
        "content": {
          "url": "Tiles/1_1/1_1.pnts"
        },
        "boundingVolume": {
          "region": [
            -2.1479366278326704,
            0.7689097003175439,
            -2.1479332260278827,
            0.7689132622519742,
            5.705856000000009,
            6.205728000000004
          ]
        },
        "geometricError": 2,
        "refine": "replace"
      }
    ],
    "content": {
      "url": "root.pnts"
    },
    "boundingVolume": {
      "region": [
        -2.147940029614008,
        0.7689061383772055,
        -2.1479332260278827,
        0.7689132622519742,
        5.705856000000009,
        27.846528000000006
      ]
    },
    "geometricError": 4,
    "refine": "replace"
  }
}