{
  "asset": {
    "version": "0.0"
  },
  "geometricError": 4,
  "root": {
    "children": [
      {
        "content": {
          "url": "Tiles/0_0/0_0.pnts"
        },
        "boundingVolume": {
          "region": [
            -2.1479873496881563,
            0.7688493070345563,
            -2.1479839482569756,
            0.7688528690572376,
            3.2674560000000086,
            41.876472
          ]
        },
        "geometricError": 2,
        "refine": "replace"
      },
      {
        "content": {
          "url": "Tiles/0_1/0_1.pnts"
        },
        "boundingVolume": {
          "region": [
            -2.147983797068228,
            0.768849387278097,
            -2.147980395624539,
            0.7688529492946942,
            3.2674560000000086,
            47.31410400000001
          ]
        },
        "geometricError": 2,
        "refine": "replace"
      },
      {
        "content": {
          "url": "Tiles/1_0/1_0.pnts"
        },
        "boundingVolume": {
          "region": [
            -2.1479875008888607,
            0.7688527888134286,
            -2.147984099446742,
            0.7688563508362877,
            3.3558479999999973,
            45.58588799999998
          ]
        },
        "geometricError": 2,
        "refine": "replace"
      },
      {
        "content": {
          "url": "Tiles/1_1/1_1.pnts"
        },
        "boundingVolume": {
          "region": [
            -2.1479839482569756,
            0.7688528690572376,
            -2.1479805468023487,
            0.7688564310740128,
            3.6576000000000004,
            47.326296
          ]
        },
        "geometricError": 2,
        "refine": "replace"
      }
    ],
    "content": {
      "url": "root.pnts"
    },
    "boundingVolume": {
      "region": [
        -2.1479873496881563,
        0.7688493070345563,
        -2.1479805468023487,
        0.7688564310740128,
        3.2674560000000086,
        47.326296
      ]
    },
    "geometricError": 4,
    "refine": "replace"
  }
}